{
	"format_version": "1.8.0",
	"animations": {
		"animation.copper_golem.idle": {
			"loop": true,
			"animation_length": 3.04167,
			"bones": {
				"left_arm": {
					"rotation": {
						"0.0": {
							"vector": [0, 0, 0]
						},
						"1.5": {
							"vector": [0, 0, 7.5]
						},
						"3.0": {
							"vector": [0, 0, 0]
						}
					}
				},
				"right_arm": {
					"rotation": {
						"0.0": {
							"vector": [0, 0, 0]
						},
						"1.5": {
							"vector": [0, 0, -7.5]
						},
						"3.0": {
							"vector": [0, 0, 0]
						}
					}
				}
			}
		},
		"animation.copper_golem.walk": {
			"loop": true,
			"animation_length": 1.375,
			"bones": {
				"left_leg": {
					"rotation": {
						"0.0": {
							"vector": [0, 0, 0]
						},
						"0.3333": {
							"vector": [-17.5, 0, 0]
						},
						"0.6667": {
							"vector": [0, 0, 0]
						},
						"1.0": {
							"vector": [17.5, 0, 0]
						},
						"1.3333": {
							"vector": [0, 0, 0]
						}
					}
				},
				"right_leg": {
					"rotation": {
						"0.0": {
							"vector": [0, 0, 0]
						},
						"0.3333": {
							"vector": [17.5, 0, 0]
						},
						"0.6667": {
							"vector": [0, 0, 0]
						},
						"1.0": {
							"vector": [-17.5, 0, 0]
						},
						"1.3333": {
							"vector": [0, 0, 0]
						}
					}
				},
				"left_arm": {
					"rotation": {
						"0.0": {
							"vector": [0, 0, 0]
						},
						"0.3333": {
							"vector": [-17.5, 0, 0]
						},
						"0.6667": {
							"vector": [0, 0, 0]
						},
						"1.0": {
							"vector": [17.5, 0, 0]
						},
						"1.3333": {
							"vector": [0, 0, 0]
						}
					}
				},
				"right_arm": {
					"rotation": {
						"0.0": {
							"vector": [0, 0, 0]
						},
						"0.3333": {
							"vector": [17.5, 0, 0]
						},
						"0.6667": {
							"vector": [0, 0, 0]
						},
						"1.0": {
							"vector": [-17.5, 0, 0]
						},
						"1.3333": {
							"vector": [0, 0, 0]
						}
					}
				}
			}
		},
		"animation.copper_golem.interact": {
			"animation_length": 1.25,
			"bones": {
				"left_arm": {
					"rotation": {
						"0.0": {
							"vector": [0, 0, 0]
						},
						"0.1667": {
							"vector": [-27.5, 0, 0]
						},
						"0.3333": {
							"vector": [-120, 0, 0]
						},
						"0.5": {
							"vector": [-27.5, 0, 0]
						},
						"0.6667": {
							"vector": [-102.5, 0, 0]
						},
						"0.8333": {
							"vector": [-60, 0, 0]
						},
						"1.0": {
							"vector": [-137.5, 0, 0]
						},
						"1.1667": {
							"vector": [0, 0, 0]
						}
					}
				},
				"right_arm": {
					"rotation": {
						"0.0": {
							"vector": [0, 0, 0]
						},
						"0.1667": {
							"vector": [-137.5, 0, 0]
						},
						"0.3333": {
							"vector": [-60, 0, 0]
						},
						"0.5": {
							"vector": [-102.5, 0, 0]
						},
						"0.6667": {
							"vector": [-27.5, 0, 0]
						},
						"0.8333": {
							"vector": [-120, 0, 0]
						},
						"1.0": {
							"vector": [-27.5, 0, 0]
						},
						"1.1667": {
							"vector": [0, 0, 0]
						}
					}
				},
				"head": {
					"rotation": {
						"0.0": {
							"vector": [0, 0, 0]
						},
						"0.1667": {
							"vector": [0, 45, 0]
						},
						"0.3333": {
							"vector": [0, 90, 0]
						},
						"0.5": {
							"vector": [0, 135, 0]
						},
						"0.6667": {
							"vector": [0, 225, 0]
						},
						"0.8333": {
							"vector": [0, 270, 0]
						},
						"1.0": {
							"vector": [0, 315, 0]
						},
						"1.1667": {
							"vector": [0, 360, 0]
						}
					}
				}
			}
		}
	},
	"geckolib_format_version": 2
}